moss/convert.py
moss/export.py
moss/parallel.py
moss/_moss.cpython-310-x86_64-linux-gnu.so
moss/engine.py
moss/__init__.py
python_moss-1.4.0.dist-info/top_level.txt
python_moss-1.4.0.dist-info/METADATA
python_moss-1.4.0.dist-info/RECORD
python_moss-1.4.0.dist-info/WHEEL
python_moss-1.4.0.dist-info/licenses/LICENSE
python_moss.libs/libnvToolsExt-847d78f2.so.1.0.0
