Metadata-Version: 2.4
Name: python-moss
Version: 1.4.0
Summary: MObility Simulation System
Author-email: Jun Zhang <zhangjun990222@gmail.com>, Wenxuan Ao <aowx21@outlook.com>, Junbo Yan <yanjb20thu@gmali.com>
License: MIT License
Project-URL: Homepage, https://moss.fiblab.net
Project-URL: Repository, https://github.com/tsinghua-fib-lab/moss.git
Project-URL: Issues, https://github.com/tsinghua-fib-lab/moss/issues
Requires-Python: >=3.9
License-File: LICENSE
Requires-Dist: shapely>=2
Requires-Dist: protobuf<5,>=3.20
Requires-Dist: numpy<2,>=1.20
Requires-Dist: pycityproto<3,>=2
Requires-Dist: numba>=0.60
Requires-Dist: tqdm
Requires-Dist: psycopg[binary,pool]<4,>=3.0
Requires-Dist: pymongo
Requires-Dist: pyproj
Requires-Dist: stringcase
Requires-Dist: ray[default]<3,>=2.0
Dynamic: license-file
